test/__init__.py
test/test_amorphous_layer.py
test/test_atom.py
test/test_structure.py
test/test_unitCell.py
udkm1Dsim/__init__.py
udkm1Dsim/helpers.py
udkm1Dsim/matlab/calc_heat_diffusion.m
udkm1Dsim/parameters/elements.dat
udkm1Dsim/parameters/atomic_form_factors/cromermann.txt
udkm1Dsim/parameters/atomic_form_factors/chantler/README.md
udkm1Dsim/parameters/atomic_form_factors/chantler/ac.cf
udkm1Dsim/parameters/atomic_form_factors/chantler/ag.cf
udkm1Dsim/parameters/atomic_form_factors/chantler/al.cf
udkm1Dsim/parameters/atomic_form_factors/chantler/ar.cf
udkm1Dsim/parameters/atomic_form_factors/chantler/as.cf
udkm1Dsim/parameters/atomic_form_factors/chantler/at.cf
udkm1Dsim/parameters/atomic_form_factors/chantler/au.cf
udkm1Dsim/parameters/atomic_form_factors/chantler/b.cf
udkm1Dsim/parameters/atomic_form_factors/chantler/ba.cf
udkm1Dsim/parameters/atomic_form_factors/chantler/be.cf
udkm1Dsim/parameters/atomic_form_factors/chantler/bi.cf
udkm1Dsim/parameters/atomic_form_factors/chantler/br.cf
udkm1Dsim/parameters/atomic_form_factors/chantler/c.cf
udkm1Dsim/parameters/atomic_form_factors/chantler/ca.cf
udkm1Dsim/parameters/atomic_form_factors/chantler/cd.cf
udkm1Dsim/parameters/atomic_form_factors/chantler/ce.cf
udkm1Dsim/parameters/atomic_form_factors/chantler/cl.cf
udkm1Dsim/parameters/atomic_form_factors/chantler/co.cf
udkm1Dsim/parameters/atomic_form_factors/chantler/cr.cf
udkm1Dsim/parameters/atomic_form_factors/chantler/cs.cf
udkm1Dsim/parameters/atomic_form_factors/chantler/cu.cf
udkm1Dsim/parameters/atomic_form_factors/chantler/dy.cf
udkm1Dsim/parameters/atomic_form_factors/chantler/er.cf
udkm1Dsim/parameters/atomic_form_factors/chantler/eu.cf
udkm1Dsim/parameters/atomic_form_factors/chantler/f.cf
udkm1Dsim/parameters/atomic_form_factors/chantler/fe.cf
udkm1Dsim/parameters/atomic_form_factors/chantler/fr.cf
udkm1Dsim/parameters/atomic_form_factors/chantler/ga.cf
udkm1Dsim/parameters/atomic_form_factors/chantler/gd.cf
udkm1Dsim-2.0.4.dist-info/LICENSE
udkm1Dsim-2.0.4.dist-info/METADATA
udkm1Dsim-2.0.4.dist-info/WHEEL
udkm1Dsim-2.0.4.dist-info/top_level.txt
udkm1Dsim-2.0.4.dist-info/RECORD
