Metadata-Version: 2.1
Name: udkm1Dsim
Version: 2.0.4
Summary: A Python Simulation Toolkit for 1D Ultrafast Dynamics in Condensed Matter
Home-page: https://github.com/dschick/udkm1Dsim
Author: Daniel Schick
Author-email: schick.daniel@gmail.com
License: MIT
Keywords: ultrafast dynamics condensed matter 1D NTM 3TM 2TM TTM N-temperature model coherent acoustic phonons sound strain waves resonant magnetic scattering diffraction spectroscopy x-ray magnetic circular dichroism Landau Lifschitz Bloch
Platform: UNKNOWN
Requires-Python: >=3.9
License-File: LICENSE
Requires-Dist: tqdm>=4.43.0
Requires-Dist: numpy<2.0.0,>=1.18.2
Requires-Dist: pint>=0.23
Requires-Dist: scipy>=1.4.1
Requires-Dist: sympy>=1.5.1
Requires-Dist: tabulate
Requires-Dist: matplotlib>=2.0.0
Provides-Extra: parallel
Requires-Dist: dask[distributed]>=2.6.0; extra == "parallel"
Provides-Extra: testing
Requires-Dist: flake8; extra == "testing"
Requires-Dist: pytest; extra == "testing"
